Flask_UrlDiscovery-1.1.1.dist-info/DESCRIPTION.rst
Flask_UrlDiscovery-1.1.1.dist-info/METADATA
Flask_UrlDiscovery-1.1.1.dist-info/RECORD
Flask_UrlDiscovery-1.1.1.dist-info/WHEEL
Flask_UrlDiscovery-1.1.1.dist-info/metadata.json
Flask_UrlDiscovery-1.1.1.dist-info/top_level.txt
flask_url_discovery/__init__.py
flask_url_discovery/app_registry.py
flask_url_discovery/env.py
flask_url_discovery/urls_privation.py
flask_url_discovery/utils.py
flask_url_discovery/version.py
