Metadata-Version: 2.0
Name: Flask-UrlDiscovery
Version: 1.1.1
Summary: A Flask extension for discovering urls in a service. Automatically exposes urls for a service
Home-page: https://github.com/UseTheApi/flask_url_discovery
Author: Alena Lifar
Author-email: alenaslifar@gmail.com
License: MIT
Platform: any
Classifier: Environment :: Web Environment
Classifier: Intended Audience :: Developers
Classifier: License :: OSI Approved :: MIT License
Classifier: Operating System :: OS Independent
Classifier: Programming Language :: Python
Classifier: Programming Language :: Python :: 2.6
Classifier: Programming Language :: Python :: 2.7
Classifier: Programming Language :: Python :: 3
Classifier: Programming Language :: Python :: Implementation :: CPython
Classifier: Programming Language :: Python :: Implementation :: PyPy
Classifier: Topic :: Internet :: WWW/HTTP :: Dynamic Content
Classifier: Topic :: Software Development :: Libraries :: Python Modules
Requires-Dist: Flask (>=0.9)
Requires-Dist: pytest (>=3.0)
Requires-Dist: requests (>=2.13)
Requires-Dist: mock (>=2.0)
